pytest_chunks/__init__.py
pytest_chunks/tests/__init__.py
pytest_chunks/tests/test_chunks.py
pytest_chunks-0.2.0.dist-info/entry_points.txt
pytest_chunks-0.2.0.dist-info/LICENSE
pytest_chunks-0.2.0.dist-info/WHEEL
pytest_chunks-0.2.0.dist-info/METADATA
pytest_chunks-0.2.0.dist-info/RECORD
